Workbook

Sheet Assumptions
A1: Morrisons LBO & Credit Analysis — Key Assumptions
A3: ENTRY ASSUMPTIONS
A4: Entry EBITDA (£m) | B4: 974 | C4: Source: Derived: FY21/22 adjusted EBITDA of £828m was reported down 15% YoY (Retail Insight Network) → implies FY20/21 EBITDA ≈ 828/0.85 ≈ £974m
A5: Entry EV / EBITDA Multiple (x) | B5: 10.3 | C5: Source: Implied by £10bn total deal value (incl. debt) reported by multiple outlets (Sky News/ICMA Centre) ÷ £974m entry EBITDA
A6: Entry Enterprise Value (£m) | B6: =B4*B5 -> 10032.2 | C6: Note: Entry EBITDA × Entry Multiple (checks to ~£10.0bn, consistent with reported deal value)
A8: OPERATING ASSUMPTIONS
A9: Year 0 Revenue (£m) | B9: 17600 | C9: Source/Note: Source: Morrisons FY20/21 turnover of ~£17.6bn (Statista / Morrisons Corporate)
A10: Annual Revenue Growth (%) | B10: 0.02 | C10: Source/Note: Assumption: broadly flat/low growth, consistent with FY21/22 actual reported growth of 2.2%
A11: Year 0 EBITDA Margin (%) | B11: =B4/B9 -> 0.055340909 | C11: Source/Note: = Entry EBITDA ÷ Year 0 Revenue (£974m ÷ £17.6bn), kept as a live formula so the two tie out exactly
A12: Annual EBITDA Margin Improvement (bps p.a.) | B12: 0.003 | C12: Source/Note: Assumption: gradual efficiency gains; directionally consistent with Morrisons' actual EBITDA recovery in later years (reported ~£970m+ in most recent period)
A13: D&A (% of Revenue) | B13: 0.025 | C13: Source/Note: Assumption: typical for capital-intensive UK grocery retail
A14: Capex (% of Revenue) | B14: 0.03 | C14: Source/Note: Assumption: maintenance + growth capex for grocery estate
A15: Increase in Net Working Capital (% of Revenue growth) | B15: 0.1 | C15: Source/Note: Assumption: modest NWC drag as revenue grows
A16: Corporate Tax Rate (%) | B16: 0.25 | C16: Source/Note: UK corporation tax rate
A18: DEBT ASSUMPTIONS
A19: Term Loan (Senior, Amortizing) at Entry (£m) | B19: 2000 | C19: Source/Note: Source: reported debt package included £2bn in term loans from banks (Grocery Gazette / BSIC), plus a separate £1bn revolving credit facility (assumed undrawn at close, not modeled as funded debt)
A20: Term Loan Interest Rate (%) | B20: 0.065 | C20: Source/Note: Assumption: reflects rising-rate environment post-2022 that squeezed Morrisons per reported coverage
A21: Term Loan Mandatory Amortisation (% of original principal p.a.) | B21: 0.01 | C21: Source/Note: Assumption: typical 1% p.a. mandatory amortisation on institutional term loans
A22: Bonds (Bullet, Non-Amortizing) at Entry (£m) | B22: 5800 | C22: Source/Note: Sized so Total Debt implies ~8.0x leverage on Entry EBITDA, matching Fitch's reported entry leverage of 'almost 8x EBITDA' at close (up from an earlier draft that used the raw £3.6bn bond figure and understated real leverage)
A23: Bond Coupon Rate (%) | B23: 0.07 | C23: Source/Note: Assumption: junk-rated bond coupon typical for a sponsor-backed retail LBO in this period
A24: Cash Sweep (% of Excess FCF applied to Term Loan) | B24: 0.75 | C24: Source/Note: Assumption: standard LBO cash sweep mechanic — bonds are bullet (no sweep), consistent with real bond structures
A25: Total Debt at Entry (£m) | B25: =B19+B22 -> 7800 | C25: Checks to ~£7.8bn (~8.0x Entry EBITDA), consistent with Fitch's reported entry leverage of 'almost 8x EBITDA' — higher than the £6.1-6.2bn absolute debt figure some outlets cited, likely because that figure was net of certain adjustments
A26: Note on leverage sizing | C26: We deliberately sized Total Debt to hit the real, reported ~8.0x entry leverage (rather than the lower ~6.2bn absolute figure), since Fitch explicitly called this level of leverage 'incompatible' with an investment-grade rating — this makes the stress test meaningfully tighter against the covenant threshold, matching the real risk profile of the deal.
A28: EXIT ASSUMPTIONS
A29: Exit Year | B29: 5 | C29: Note: Assumption: standard 5-year hold period
A30: Exit EV / EBITDA Multiple (x) | B30: 10.3 | C30: Note: Assumption: exit at same multiple as entry (no multiple expansion assumed — conservative base case)
A32: COVENANT THRESHOLDS (illustrative, for stress-testing)
A33: Maximum Leverage Covenant (Net Debt / EBITDA, x) | B33: 6.5 | C33: Note: Illustrative senior facility leverage covenant
A34: Minimum Interest Coverage Covenant (EBITDA / Interest, x) | B34: 2 | C34: Note: Illustrative senior facility coverage covenant

Sheet Sources & Uses
A1: Sources & Uses of Funds (at Entry)
A3: USES
A4: Purchase of Enterprise Value | B4: =Assumptions!$B$6 -> 10032.2
A5: Transaction Fees & Expenses (2.0% of EV) | B5: =B4*0.02 -> 200.644
A6: Total Uses | B6: =SUM(B4:B5) -> 10232.844
A8: SOURCES
A9: Senior Term Loan | B9: =Assumptions!$B$19 -> 2000
A10: Subordinated / Mezzanine Debt | B10: =Assumptions!$B$22 -> 5800
A11: Sponsor Equity (plug) | B11: =B6-B9-B10 -> 2432.844
A12: Total Sources | B12: =SUM(B9:B11) -> 10232.844
A14: Balance Check (Sources - Uses) | B14: =B12-B6 -> 0

Sheet Operating Model
A1: Operating Model (£m)
B2: Year 0 (Entry) | C2: Year 1 | D2: Year 2 | E2: Year 3 | F2: Year 4 | G2: Year 5 (Exit)
A3: Revenue | B3: =Assumptions!$B$9 -> 17600 | C3: =B3*(1+C4) -> 17952 | D3: =C3*(1+D4) -> 18311.04 | E3: =D3*(1+E4) -> 18677.261 | F3: =E3*(1+F4) -> 19050.806 | G3: =F3*(1+G4) -> 19431.822
A4: Revenue Growth (%) | B4: n/a | C4: =Assumptions!$B$10 -> 0.02 | D4: =Assumptions!$B$10 -> 0.02 | E4: =Assumptions!$B$10 -> 0.02 | F4: =Assumptions!$B$10 -> 0.02 | G4: =Assumptions!$B$10 -> 0.02
A5: EBITDA Margin (%) | B5: =Assumptions!$B$11 -> 0.055340909 | C5: =B5+Assumptions!$B$12 -> 0.058340909 | D5: =C5+Assumptions!$B$12 -> 0.061340909 | E5: =D5+Assumptions!$B$12 -> 0.064340909 | F5: =E5+Assumptions!$B$12 -> 0.067340909 | G5: =F5+Assumptions!$B$12 -> 0.070340909
A6: EBITDA | B6: =B3*B5 -> 974 | C6: =C3*C5 -> 1047.336 | D6: =D3*D5 -> 1123.2158 | E6: =E3*E5 -> 1201.7119 | F6: =F3*F5 -> 1282.8986 | G6: =G3*G5 -> 1366.852
A7: D&A | B7: =B3*Assumptions!$B$13 -> 440 | C7: =C3*Assumptions!$B$13 -> 448.8 | D7: =D3*Assumptions!$B$13 -> 457.776 | E7: =E3*Assumptions!$B$13 -> 466.93152 | F7: =F3*Assumptions!$B$13 -> 476.27015 | G7: =G3*Assumptions!$B$13 -> 485.79555
A8: EBIT | B8: =B6-B7 -> 534 | C8: =C6-C7 -> 598.536 | D8: =D6-D7 -> 665.43984 | E8: =E6-E7 -> 734.78042 | F8: =F6-F7 -> 806.62845 | G8: =G6-G7 -> 881.05648
A9: Interest Expense | B9: ='Debt Schedule'!B17 -> 0 | C9: ='Debt Schedule'!C17 -> 536 | D9: ='Debt Schedule'!D17 -> 534.7 | E9: ='Debt Schedule'!E17 -> 533.4 | F9: ='Debt Schedule'!F17 -> 532.04994 | G9: ='Debt Schedule'!G17 -> 528.15033
A10: EBT | B10: =B8-B9 -> 534 | C10: =C8-C9 -> 62.536 | D10: =D8-D9 -> 130.73984 | E10: =E8-E9 -> 201.38042 | F10: =F8-F9 -> 274.57851 | G10: =G8-G9 -> 352.90615
A11: Taxes | B11: =MAX(0,B10)*Assumptions!$B$16 -> 133.5 | C11: =MAX(0,C10)*Assumptions!$B$16 -> 15.634 | D11: =MAX(0,D10)*Assumptions!$B$16 -> 32.68496 | E11: =MAX(0,E10)*Assumptions!$B$16 -> 50.345105 | F11: =MAX(0,F10)*Assumptions!$B$16 -> 68.644627 | G11: =MAX(0,G10)*Assumptions!$B$16 -> 88.226538
A12: Net Income | B12: =B10-B11 -> 400.5 | C12: =C10-C11 -> 46.902 | D12: =D10-D11 -> 98.05488 | E12: =E10-E11 -> 151.03531 | F12: =F10-F11 -> 205.93388 | G12: =G10-G11 -> 264.67962
A13: (+) D&A | B13: =B7 -> 440 | C13: =C7 -> 448.8 | D13: =D7 -> 457.776 | E13: =E7 -> 466.93152 | F13: =F7 -> 476.27015 | G13: =G7 -> 485.79555
A14: (-) Capex | B14: =B3*Assumptions!$B$14 -> 528 | C14: =C3*Assumptions!$B$14 -> 538.56 | D14: =D3*Assumptions!$B$14 -> 549.3312 | E14: =E3*Assumptions!$B$14 -> 560.31782 | F14: =F3*Assumptions!$B$14 -> 571.52418 | G14: =G3*Assumptions!$B$14 -> 582.95466
A15: (-) Increase in NWC | B15: 0 | C15: =(C3-B3)*Assumptions!$B$15 -> 35.2 | D15: =(D3-C3)*Assumptions!$B$15 -> 35.904 | E15: =(E3-D3)*Assumptions!$B$15 -> 36.62208 | F15: =(F3-E3)*Assumptions!$B$15 -> 37.354522 | G15: =(G3-F3)*Assumptions!$B$15 -> 38.101612
A16: Free Cash Flow (pre debt service) | B16: =B12+B13-B14-B15 -> 312.5 | C16: =C12+C13-C14-C15 -> -78.058 | D16: =D12+D13-D14-D15 -> -29.40432 | E16: =E12+E13-E14-E15 -> 21.02693 | F16: =F12+F13-F14-F15 -> 73.32533 | G16: =G12+G13-G14-G15 -> 129.41889

Sheet Debt Schedule
A1: Debt Schedule (£m)
B2: Year 0 (Entry) | C2: Year 1 | D2: Year 2 | E2: Year 3 | F2: Year 4 | G2: Year 5 (Exit)
A3: SENIOR TERM LOAN
A4: Opening Balance | B4: =Assumptions!$B$19 -> 2000 | C4: =B7 -> 2000 | D4: =C7 -> 1980 | E4: =D7 -> 1960 | F4: =E7 -> 1939.2298 | G4: =F7 -> 1879.2358
A5: Mandatory Amortisation | B5: 0 | C5: =MIN(C4,Assumptions!$B$19*Assumptions!$B$21) -> 20 | D5: =MIN(D4,Assumptions!$B$19*Assumptions!$B$21) -> 20 | E5: =MIN(E4,Assumptions!$B$19*Assumptions!$B$21) -> 20 | F5: =MIN(F4,Assumptions!$B$19*Assumptions!$B$21) -> 20 | G5: =MIN(G4,Assumptions!$B$19*Assumptions!$B$21) -> 20
A6: Cash Sweep (Optional Paydown) | B6: 0 | C6: =MIN(C18*Assumptions!$B$24,C4-C5) -> 0 | D6: =MIN(D18*Assumptions!$B$24,D4-D5) -> 0 | E6: =MIN(E18*Assumptions!$B$24,E4-E5) -> 0.7701978 | F6: =MIN(F18*Assumptions!$B$24,F4-F5) -> 39.993997 | G6: =MIN(G18*Assumptions!$B$24,G4-G5) -> 82.064169
A7: Closing Balance | B7: =B4-B5-B6 -> 2000 | C7: =C4-C5-C6 -> 1980 | D7: =D4-D5-D6 -> 1960 | E7: =E4-E5-E6 -> 1939.2298 | F7: =F4-F5-F6 -> 1879.2358 | G7: =G4-G5-G6 -> 1777.1716
A8: Interest Expense (on Opening Balance) | B8: 0 | C8: =C4*Assumptions!$B$20 -> 130 | D8: =D4*Assumptions!$B$20 -> 128.7 | E8: =E4*Assumptions!$B$20 -> 127.4 | F8: =F4*Assumptions!$B$20 -> 126.04994 | G8: =G4*Assumptions!$B$20 -> 122.15033
A10: BONDS (BULLET — NO AMORTISATION)
A11: Opening Balance | B11: =Assumptions!$B$22 -> 5800 | C11: =B12 -> 5800 | D11: =C12 -> 5800 | E11: =D12 -> 5800 | F11: =E12 -> 5800 | G11: =F12 -> 5800
A12: Closing Balance (bullet — bonds are not amortized/swept, repaid at exit) | B12: =B11 -> 5800 | C12: =C11 -> 5800 | D12: =D11 -> 5800 | E12: =E11 -> 5800 | F12: =F11 -> 5800 | G12: =G11 -> 5800
A13: Interest Expense (on Opening Balance) | B13: 0 | C13: =C11*Assumptions!$B$23 -> 406 | D13: =D11*Assumptions!$B$23 -> 406 | E13: =E11*Assumptions!$B$23 -> 406 | F13: =F11*Assumptions!$B$23 -> 406 | G13: =G11*Assumptions!$B$23 -> 406
A15: TOTAL
A16: Total Debt (Closing) | B16: =B7+B12 -> 7800 | C16: =C7+C12 -> 7780 | D16: =D7+D12 -> 7760 | E16: =E7+E12 -> 7739.2298 | F16: =F7+F12 -> 7679.2358 | G16: =G7+G12 -> 7577.1716
A17: Total Interest Expense | B17: =B8+B13 -> 0 | C17: =C8+C13 -> 536 | D17: =D8+D13 -> 534.7 | E17: =E8+E13 -> 533.4 | F17: =F8+F13 -> 532.04994 | G17: =G8+G13 -> 528.15033
A18: Cash Available for Sweep (pre-sweep FCF less mandatory amort) | B18: 0 | C18: =MAX(0,'Operating Model'!C16-C5) -> 0 | D18: =MAX(0,'Operating Model'!D16-D5) -> 0 | E18: =MAX(0,'Operating Model'!E16-E5) -> 1.0269304 | F18: =MAX(0,'Operating Model'!F16-F5) -> 53.32533 | G18: =MAX(0,'Operating Model'!G16-G5) -> 109.41889

Sheet Credit Metrics
A1: Credit Metrics & Covenant Analysis
B2: Year 0 (Entry) | C2: Year 1 | D2: Year 2 | E2: Year 3 | F2: Year 4 | G2: Year 5 (Exit)
A3: EBITDA (£m) | B3: ='Operating Model'!B6 -> 974 | C3: ='Operating Model'!C6 -> 1047.336 | D3: ='Operating Model'!D6 -> 1123.2158 | E3: ='Operating Model'!E6 -> 1201.7119 | F3: ='Operating Model'!F6 -> 1282.8986 | G3: ='Operating Model'!G6 -> 1366.852
A4: Total Debt (£m) | B4: ='Debt Schedule'!B16 -> 7800 | C4: ='Debt Schedule'!C16 -> 7780 | D4: ='Debt Schedule'!D16 -> 7760 | E4: ='Debt Schedule'!E16 -> 7739.2298 | F4: ='Debt Schedule'!F16 -> 7679.2358 | G4: ='Debt Schedule'!G16 -> 7577.1716
A5: Leverage Ratio (Debt / EBITDA) | B5: =IFERROR(B4/B3,0) -> 8.0082136 | C5: =IFERROR(C4/C3,0) -> 7.4283706 | D5: =IFERROR(D4/D3,0) -> 6.9087345 | E5: =IFERROR(E4/E3,0) -> 6.4401705 | F5: =IFERROR(F4/F3,0) -> 5.9858479 | G5: =IFERROR(G4/G3,0) -> 5.54352
A6: Interest Expense (£m) | B6: ='Operating Model'!B9 -> 0 | C6: ='Operating Model'!C9 -> 536 | D6: ='Operating Model'!D9 -> 534.7 | E6: ='Operating Model'!E9 -> 533.4 | F6: ='Operating Model'!F9 -> 532.04994 | G6: ='Operating Model'!G9 -> 528.15033
A7: Interest Coverage Ratio (EBITDA / Interest) | B7: n/a | C7: =IFERROR(C3/C6,0) -> 1.9539851 | D7: =IFERROR(D3/D6,0) -> 2.1006468 | E7: =IFERROR(E3/E6,0) -> 2.2529283 | F7: =IFERROR(F3/F6,0) -> 2.4112372 | G7: =IFERROR(G3/G6,0) -> 2.5879981
A8: Free Cash Flow (pre debt service, £m) | B8: ='Operating Model'!B16 -> 312.5 | C8: ='Operating Model'!C16 -> -78.058 | D8: ='Operating Model'!D16 -> -29.40432 | E8: ='Operating Model'!E16 -> 21.02693 | F8: ='Operating Model'!F16 -> 73.32533 | G8: ='Operating Model'!G16 -> 129.41889
A9: Mandatory Debt Service (Amort + Interest, £m) | B9: ='Debt Schedule'!B5+B6 -> 0 | C9: ='Debt Schedule'!C5+C6 -> 556 | D9: ='Debt Schedule'!D5+D6 -> 554.7 | E9: ='Debt Schedule'!E5+E6 -> 553.4 | F9: ='Debt Schedule'!F5+F6 -> 552.04994 | G9: ='Debt Schedule'!G5+G6 -> 548.15033
A10: FCF / Debt Service Coverage | B10: n/a | C10: =IFERROR(C8/C9,0) -> -0.14039209 | D10: =IFERROR(D8/D9,0) -> -0.05300941 | E10: =IFERROR(E8/E9,0) -> 0.037995899 | F10: =IFERROR(F8/F9,0) -> 0.13282373 | G10: =IFERROR(G8/G9,0) -> 0.2361011
A12: Leverage Covenant Threshold (Max) | B12: =Assumptions!$B$33 -> 6.5 | C12: =Assumptions!$B$33 -> 6.5 | D12: =Assumptions!$B$33 -> 6.5 | E12: =Assumptions!$B$33 -> 6.5 | F12: =Assumptions!$B$33 -> 6.5 | G12: =Assumptions!$B$33 -> 6.5
A13: Leverage Covenant Headroom (x) | B13: =B12-B5 -> -1.5082136 | C13: =C12-C5 -> -0.92837065 | D13: =D12-D5 -> -0.40873448 | E13: =E12-E5 -> 0.059829482 | F13: =F12-F5 -> 0.51415215 | G13: =G12-G5 -> 0.95647997
A14: Leverage Covenant Status | B14: =IF(B5>B12,"BREACH","OK") -> BREACH | C14: =IF(C5>C12,"BREACH","OK") -> BREACH | D14: =IF(D5>D12,"BREACH","OK") -> BREACH | E14: =IF(E5>E12,"BREACH","OK") -> OK | F14: =IF(F5>F12,"BREACH","OK") -> OK | G14: =IF(G5>G12,"BREACH","OK") -> OK
A16: Coverage Covenant Threshold (Min) | B16: =Assumptions!$B$34 -> 2 | C16: =Assumptions!$B$34 -> 2 | D16: =Assumptions!$B$34 -> 2 | E16: =Assumptions!$B$34 -> 2 | F16: =Assumptions!$B$34 -> 2 | G16: =Assumptions!$B$34 -> 2
A17: Coverage Covenant Headroom (x) | B17: n/a | C17: =C7-C16 -> -0.046014925 | D17: =D7-D16 -> 0.10064679 | E17: =E7-E16 -> 0.25292827 | F17: =F7-F16 -> 0.41123719 | G17: =G7-G16 -> 0.58799808
A18: Coverage Covenant Status | B18: n/a | C18: =IF(C7<C16,"BREACH","OK") -> BREACH | D18: =IF(D7<D16,"BREACH","OK") -> OK | E18: =IF(E7<E16,"BREACH","OK") -> OK | F18: =IF(F7<F16,"BREACH","OK") -> OK | G18: =IF(G7<G16,"BREACH","OK") -> OK

Sheet Returns
A1: Returns Analysis
A3: EXIT VALUATION
A4: Exit Year EBITDA (£m) | B4: ='Operating Model'!G6 -> 1366.852
A5: Exit EV / EBITDA Multiple (x) | B5: =Assumptions!$B$30 -> 10.3
A6: Exit Enterprise Value (£m) | B6: =B4*B5 -> 14078.576
A7: Less: Exit Net Debt (£m) | B7: ='Debt Schedule'!G16 -> 7577.1716
A8: Exit Equity Value (£m) | B8: =B6-B7 -> 6501.4043
A10: SPONSOR RETURNS
A11: Entry Sponsor Equity (£m) | B11: ='Sources & Uses'!B11 -> 2432.844
A12: Exit Equity Value (£m) | B12: =B8 -> 6501.4043
A13: Money Multiple (MOIC) | B13: =B8/B11 -> 2.6723474
A14: Holding Period (Years) | B14: =Assumptions!$B$29 -> 5
A15: Implied IRR (%) | B15: =(B8/B11)^(1/B14)-1 -> 0.21724664
